<?xml version="1.0" encoding="utf-8" ?>
<dwsync>
<file name="cp1250.map" server="C:/wamp/www/UsPage/" local="126655802520000000" remote="126655802520000000" />
<file name="cp1250.map" server="" local="126655802520000000" remote="99273120295646067" />
<file name="cp1251.map" server="C:/wamp/www/UsPage/" local="126645355840000000" remote="126645355840000000" />
<file name="cp1251.map" server="" local="126645355840000000" remote="99273120295646067" />
<file name="cp1252.map" server="C:/wamp/www/UsPage/" local="126645355840000000" remote="126645355840000000" />
<file name="cp1252.map" server="" local="126645355840000000" remote="99273120295646067" />
<file name="cp1253.map" server="C:/wamp/www/UsPage/" local="126650529360000000" remote="126650529360000000" />
<file name="cp1253.map" server="" local="126650529360000000" remote="99273120295646067" />
<file name="cp1254.map" server="C:/wamp/www/UsPage/" local="126806386080000000" remote="126806386080000000" />
<file name="cp1254.map" server="" local="126806386080000000" remote="99273120295646067" />
<file name="cp1255.map" server="C:/wamp/www/UsPage/" local="127001465540000000" remote="127001465540000000" />
<file name="cp1255.map" server="" local="127001465540000000" remote="99273120295646067" />
<file name="cp1257.map" server="C:/wamp/www/UsPage/" local="126725734460000000" remote="126725734460000000" />
<file name="cp1257.map" server="" local="126725734460000000" remote="99273120295646067" />
<file name="cp1258.map" server="C:/wamp/www/UsPage/" local="127172731060000000" remote="127172731060000000" />
<file name="cp1258.map" server="" local="127172731060000000" remote="99273120295646067" />
<file name="cp874.map" server="C:/wamp/www/UsPage/" local="126897806440000000" remote="126897806440000000" />
<file name="cp874.map" server="" local="126897806440000000" remote="99273120295646067" />
<file name="iso-8859-1.map" server="C:/wamp/www/UsPage/" local="126653019680000000" remote="126653019680000000" />
<file name="iso-8859-1.map" server="" local="126653019680000000" remote="99273120295646067" />
<file name="iso-8859-11.map" server="C:/wamp/www/UsPage/" local="126897805540000000" remote="126897805540000000" />
<file name="iso-8859-11.map" server="" local="126897805540000000" remote="99273120295646067" />
<file name="iso-8859-15.map" server="C:/wamp/www/UsPage/" local="126653018960000000" remote="126653018960000000" />
<file name="iso-8859-15.map" server="" local="126653018960000000" remote="99273120295646067" />
<file name="iso-8859-16.map" server="C:/wamp/www/UsPage/" local="126653033800000000" remote="126653033800000000" />
<file name="iso-8859-16.map" server="" local="126653033800000000" remote="99273120295646067" />
<file name="iso-8859-2.map" server="C:/wamp/www/UsPage/" local="126653020460000000" remote="126653020460000000" />
<file name="iso-8859-2.map" server="" local="126653020460000000" remote="99273120295646067" />
<file name="iso-8859-4.map" server="C:/wamp/www/UsPage/" local="126725731500000000" remote="126725731500000000" />
<file name="iso-8859-4.map" server="" local="126725731500000000" remote="99273120295646067" />
<file name="iso-8859-5.map" server="C:/wamp/www/UsPage/" local="126653099100000000" remote="126653099100000000" />
<file name="iso-8859-5.map" server="" local="126653099100000000" remote="99273120295646067" />
<file name="iso-8859-7.map" server="C:/wamp/www/UsPage/" local="126653138820000000" remote="126653138820000000" />
<file name="iso-8859-7.map" server="" local="126653138820000000" remote="99273120295646067" />
<file name="iso-8859-9.map" server="C:/wamp/www/UsPage/" local="126807088460000000" remote="126807088460000000" />
<file name="iso-8859-9.map" server="" local="126807088460000000" remote="99273120295646067" />
<file name="koi8-r.map" server="C:/wamp/www/UsPage/" local="126653125520000000" remote="126653125520000000" />
<file name="koi8-r.map" server="" local="126653125520000000" remote="99273120295646067" />
<file name="koi8-u.map" server="C:/wamp/www/UsPage/" local="127170858560000000" remote="127170858560000000" />
<file name="koi8-u.map" server="" local="127170858560000000" remote="99273120295646067" />
<file name="makefont.php" server="C:/wamp/www/UsPage/" local="128622012220000000" remote="128622012220000000" />
<file name="makefont.php" server="" local="128622012220000000" remote="99273120295646067" />
<file name="cp1250.map" server="C:/wamp/www/Us/" local="126655802520000000" remote="126655802520000000" />
<file name="cp1251.map" server="C:/wamp/www/Us/" local="126645355840000000" remote="126645355840000000" />
<file name="cp1252.map" server="C:/wamp/www/Us/" local="126645355840000000" remote="126645355840000000" />
<file name="cp1253.map" server="C:/wamp/www/Us/" local="126650529360000000" remote="126650529360000000" />
<file name="cp1254.map" server="C:/wamp/www/Us/" local="126806386080000000" remote="126806386080000000" />
<file name="cp1255.map" server="C:/wamp/www/Us/" local="127001465540000000" remote="127001465540000000" />
<file name="cp1257.map" server="C:/wamp/www/Us/" local="126725734460000000" remote="126725734460000000" />
<file name="cp1258.map" server="C:/wamp/www/Us/" local="127172731060000000" remote="127172731060000000" />
<file name="cp874.map" server="C:/wamp/www/Us/" local="126897806440000000" remote="126897806440000000" />
<file name="iso-8859-1.map" server="C:/wamp/www/Us/" local="126653019680000000" remote="126653019680000000" />
<file name="iso-8859-11.map" server="C:/wamp/www/Us/" local="126897805540000000" remote="126897805540000000" />
<file name="iso-8859-15.map" server="C:/wamp/www/Us/" local="126653018960000000" remote="126653018960000000" />
<file name="iso-8859-16.map" server="C:/wamp/www/Us/" local="126653033800000000" remote="126653033800000000" />
<file name="iso-8859-2.map" server="C:/wamp/www/Us/" local="126653020460000000" remote="126653020460000000" />
<file name="iso-8859-4.map" server="C:/wamp/www/Us/" local="126725731500000000" remote="126725731500000000" />
<file name="iso-8859-5.map" server="C:/wamp/www/Us/" local="126653099100000000" remote="126653099100000000" />
<file name="iso-8859-7.map" server="C:/wamp/www/Us/" local="126653138820000000" remote="126653138820000000" />
<file name="iso-8859-9.map" server="C:/wamp/www/Us/" local="126807088460000000" remote="126807088460000000" />
<file name="koi8-r.map" server="C:/wamp/www/Us/" local="126653125520000000" remote="126653125520000000" />
<file name="koi8-u.map" server="C:/wamp/www/Us/" local="127170858560000000" remote="127170858560000000" />
<file name="makefont.php" server="C:/wamp/www/Us/" local="128622012220000000" remote="128622012220000000" />
<file name="cp1250.map" server="C:/wamp/www/Formatos/" local="126655802520000000" remote="126655802520000000" />
<file name="cp1251.map" server="C:/wamp/www/Formatos/" local="126645355840000000" remote="126645355840000000" />
<file name="cp1252.map" server="C:/wamp/www/Formatos/" local="126645355840000000" remote="126645355840000000" />
<file name="cp1253.map" server="C:/wamp/www/Formatos/" local="126650529360000000" remote="126650529360000000" />
<file name="cp1254.map" server="C:/wamp/www/Formatos/" local="126806386080000000" remote="126806386080000000" />
<file name="cp1255.map" server="C:/wamp/www/Formatos/" local="127001465540000000" remote="127001465540000000" />
<file name="cp1257.map" server="C:/wamp/www/Formatos/" local="126725734460000000" remote="126725734460000000" />
<file name="cp1258.map" server="C:/wamp/www/Formatos/" local="127172731060000000" remote="127172731060000000" />
<file name="cp874.map" server="C:/wamp/www/Formatos/" local="126897806440000000" remote="126897806440000000" />
<file name="iso-8859-1.map" server="C:/wamp/www/Formatos/" local="126653019680000000" remote="126653019680000000" />
<file name="iso-8859-11.map" server="C:/wamp/www/Formatos/" local="126897805540000000" remote="126897805540000000" />
<file name="iso-8859-15.map" server="C:/wamp/www/Formatos/" local="126653018960000000" remote="126653018960000000" />
<file name="iso-8859-16.map" server="C:/wamp/www/Formatos/" local="126653033800000000" remote="126653033800000000" />
<file name="iso-8859-2.map" server="C:/wamp/www/Formatos/" local="126653020460000000" remote="126653020460000000" />
<file name="iso-8859-4.map" server="C:/wamp/www/Formatos/" local="126725731500000000" remote="126725731500000000" />
<file name="iso-8859-5.map" server="C:/wamp/www/Formatos/" local="126653099100000000" remote="126653099100000000" />
<file name="iso-8859-7.map" server="C:/wamp/www/Formatos/" local="126653138820000000" remote="126653138820000000" />
<file name="iso-8859-9.map" server="C:/wamp/www/Formatos/" local="126807088460000000" remote="126807088460000000" />
<file name="koi8-r.map" server="C:/wamp/www/Formatos/" local="126653125520000000" remote="126653125520000000" />
<file name="koi8-u.map" server="C:/wamp/www/Formatos/" local="127170858560000000" remote="127170858560000000" />
<file name="makefont.php" server="C:/wamp/www/Formatos/" local="128622012220000000" remote="128622012220000000" />
<file name="cp1250.map" server="C:/wamp/www/Format/" local="126655874520000000" remote="126655874520000000" />
<file name="cp1251.map" server="C:/wamp/www/Format/" local="126645427840000000" remote="126645427840000000" />
<file name="cp1252.map" server="C:/wamp/www/Format/" local="126645427840000000" remote="126645427840000000" />
<file name="cp1253.map" server="C:/wamp/www/Format/" local="126650601360000000" remote="126650601360000000" />
<file name="cp1254.map" server="C:/wamp/www/Format/" local="126806458080000000" remote="126806458080000000" />
<file name="cp1255.map" server="C:/wamp/www/Format/" local="127001537540000000" remote="127001537540000000" />
<file name="cp1257.map" server="C:/wamp/www/Format/" local="126725806460000000" remote="126725806460000000" />
<file name="cp1258.map" server="C:/wamp/www/Format/" local="127172803060000000" remote="127172803060000000" />
<file name="cp874.map" server="C:/wamp/www/Format/" local="126897878440000000" remote="126897878440000000" />
<file name="iso-8859-1.map" server="C:/wamp/www/Format/" local="126653091680000000" remote="126653091680000000" />
<file name="iso-8859-11.map" server="C:/wamp/www/Format/" local="126897877540000000" remote="126897877540000000" />
<file name="iso-8859-15.map" server="C:/wamp/www/Format/" local="126653090960000000" remote="126653090960000000" />
<file name="iso-8859-16.map" server="C:/wamp/www/Format/" local="126653105800000000" remote="126653105800000000" />
<file name="iso-8859-2.map" server="C:/wamp/www/Format/" local="126653092460000000" remote="126653092460000000" />
<file name="iso-8859-4.map" server="C:/wamp/www/Format/" local="126725803500000000" remote="126725803500000000" />
<file name="iso-8859-5.map" server="C:/wamp/www/Format/" local="126653171100000000" remote="126653171100000000" />
<file name="iso-8859-7.map" server="C:/wamp/www/Format/" local="126653210820000000" remote="126653210820000000" />
<file name="iso-8859-9.map" server="C:/wamp/www/Format/" local="126807160460000000" remote="126807160460000000" />
<file name="koi8-r.map" server="C:/wamp/www/Format/" local="126653197520000000" remote="126653197520000000" />
<file name="koi8-u.map" server="C:/wamp/www/Format/" local="127170930560000000" remote="127170930560000000" />
<file name="makefont.php" server="C:/wamp/www/Format/" local="128622084220000000" remote="128622084220000000" />
</dwsync>